[{
    "id": 1,
    "profile": "https://i.imgur.com/ZiIgt49.jpg",
    "name": "Vanshika Singh",
    "content":"Myself Vanshika Singh from Electronics Engineering placed in Microsoft, For me, KY is really a big celebration. It hypes up not just me but a large numbet of people in the college and even the city. It is something that clearly disproves the fact that IITians are only Nerds.",
    "designation": "Co-Convenor",
    "fb": "https://www.facebook.com/kashiyatra.IITBHU/",
    "github": "https://www.facebook.com/kashiyatra.IITBHU/"
  }
]
